[
  {
    "id": 0,
    "name": "Показники магазину",
    "position": "Всі продавці",
    "initials": "ALL",
    "gradient": "linear-gradient(135deg, #434343 0%, #000000 100%)",
    "metrics": {
      "ТО": {
        "value": 616905.0,
        "label": "ТО",
        "unit": "грн"
      },
      "Шт.": {
        "value": 86.0,
        "label": "Шт.",
        "unit": "шт"
      },
      "Чеки": {
        "value": 60.0,
        "label": "Чеки",
        "unit": "шт"
      },
      "ASP": {
        "value": 7190,
        "label": "ASP",
        "unit": "грн"
      },
      "Ср. Чек": {
        "value": 10282,
        "label": "Ср. Чек",
        "unit": "грн"
      },
      "КПЧ": {
        "value": 1.43,
        "label": "КПЧ",
        "unit": "грн"
      },
      "ACC": {
        "value": 38510.0,
        "label": "ACC",
        "unit": "грн"
      },
      "Послуги грн": {
        "value": 21129.0,
        "label": "Послуги грн",
        "unit": "грн"
      },
      "ПЧ": {
        "value": 4.0,
        "label": "ПЧ",
        "unit": "шт"
      },
      "УДС": {
        "value": 46948.8,
        "label": "УДС",
        "unit": "грн"
      },
      "% Доля ACC": {
        "value": 6.24,
        "label": "% Доля ACC",
        "unit": "%"
      },
      "Доля Послуг": {
        "value": 3.43,
        "label": "Доля Послуг",
        "unit": "%"
      },
      "Конверсія ПК": {
        "value": 18.87,
        "label": "Конверсія ПК",
        "unit": "%"
      },
      "Конверсія ПК Offline": {
        "value": 13.02,
        "label": "Конверсія ПК Offline",
        "unit": "%"
      },
      "Доля УДС": {
        "value": 2.97,
        "label": "Доля УДС",
        "unit": "%"
      }
    }
  },
  {
    "id": 1,
    "name": "Алтухов Олександр Сергійович",
    "position": "продавец-консультант",
    "initials": "АО",
    "gradient": "linear-gradient(135deg, #FF6B6B 0%, #EE5253 100%)",
    "metrics": {
      "ТО": {
        "value": 220968.0,
        "label": "ТО",
        "unit": "грн"
      },
      "Шт.": {
        "value": 18.0,
        "label": "Шт.",
        "unit": "шт"
      },
      "Чеки": {
        "value": 15.0,
        "label": "Чеки",
        "unit": "шт"
      },
      "ASP": {
        "value": 12276.0,
        "label": "ASP",
        "unit": "грн"
      },
      "Ср. Чек": {
        "value": 14731.0,
        "label": "Ср. Чек",
        "unit": "грн"
      },
      "КПЧ": {
        "value": 1.2,
        "label": "КПЧ",
        "unit": "грн"
      },
      "ACC": {
        "value": 2526.0,
        "label": "ACC",
        "unit": "грн"
      },
      "% Доля ACC": {
        "value": 1.14,
        "label": "% Доля ACC",
        "unit": "%"
      },
      "Послуги грн": {
        "value": 4197.0,
        "label": "Послуги грн",
        "unit": "грн"
      },
      "Доля Послуг": {
        "value": 1.9,
        "label": "Доля Послуг",
        "unit": "%"
      },
      "ПЧ": {
        "value": 1.0,
        "label": "ПЧ",
        "unit": "шт"
      },
      "Конверсія ПК": {
        "value": 42.45,
        "label": "Конверсія ПК",
        "unit": "%"
      },
      "Конверсія ПК Offline": {
        "value": 34.29,
        "label": "Конверсія ПК Offline",
        "unit": "%"
      },
      "УДС": {
        "value": 9899.0,
        "label": "УДС",
        "unit": "грн"
      },
      "Доля УДС": {
        "value": 4.48,
        "label": "Доля УДС",
        "unit": "%"
      }
    }
  },
  {
    "id": 2,
    "name": "Бондаренко Володимир Володимирович",
    "position": "продавец-консультант",
    "initials": "БВ",
    "gradient": "linear-gradient(135deg, #4834d4 0%, #686de0 100%)",
    "metrics": {
      "ТО": {
        "value": 167271.0,
        "label": "ТО",
        "unit": "грн"
      },
      "Шт.": {
        "value": 13.0,
        "label": "Шт.",
        "unit": "шт"
      },
      "Чеки": {
        "value": 11.0,
        "label": "Чеки",
        "unit": "шт"
      },
      "ASP": {
        "value": 12867.0,
        "label": "ASP",
        "unit": "грн"
      },
      "Ср. Чек": {
        "value": 15206.0,
        "label": "Ср. Чек",
        "unit": "грн"
      },
      "КПЧ": {
        "value": 1.18,
        "label": "КПЧ",
        "unit": "грн"
      },
      "ACC": {
        "value": 7376.0,
        "label": "ACC",
        "unit": "грн"
      },
      "% Доля ACC": {
        "value": 4.41,
        "label": "% Доля ACC",
        "unit": "%"
      },
      "Послуги грн": {
        "value": 3298.0,
        "label": "Послуги грн",
        "unit": "грн"
      },
      "Доля Послуг": {
        "value": 1.97,
        "label": "Доля Послуг",
        "unit": "%"
      },
      "ПЧ": {
        "value": 0.0,
        "label": "ПЧ",
        "unit": "шт"
      },
      "Конверсія ПК": {
        "value": 31.13,
        "label": "Конверсія ПК",
        "unit": "%"
      },
      "Конверсія ПК Offline": {
        "value": 20.0,
        "label": "Конверсія ПК Offline",
        "unit": "%"
      },
      "УДС": {
        "value": 18999.9,
        "label": "УДС",
        "unit": "грн"
      },
      "Доля УДС": {
        "value": 11.36,
        "label": "Доля УДС",
        "unit": "%"
      }
    }
  },
  {
    "id": 3,
    "name": "Колодяжний Сергій Васильович",
    "position": "продавец-консультант",
    "initials": "КС",
    "gradient": "linear-gradient(135deg, #2ecc71 0%, #27ae60 100%)",
    "metrics": {
      "ТО": {
        "value": 165636.0,
        "label": "ТО",
        "unit": "грн"
      },
      "Шт.": {
        "value": 33.0,
        "label": "Шт.",
        "unit": "шт"
      },
      "Чеки": {
        "value": 21.0,
        "label": "Чеки",
        "unit": "шт"
      },
      "ASP": {
        "value": 5019.0,
        "label": "ASP",
        "unit": "грн"
      },
      "Ср. Чек": {
        "value": 7887.0,
        "label": "Ср. Чек",
        "unit": "грн"
      },
      "КПЧ": {
        "value": 1.57,
        "label": "КПЧ",
        "unit": "грн"
      },
      "ACC": {
        "value": 18508.0,
        "label": "ACC",
        "unit": "грн"
      },
      "% Доля ACC": {
        "value": 11.17,
        "label": "% Доля ACC",
        "unit": "%"
      },
      "Послуги грн": {
        "value": 11235.0,
        "label": "Послуги грн",
        "unit": "грн"
      },
      "Доля Послуг": {
        "value": 6.78,
        "label": "Доля Послуг",
        "unit": "%"
      },
      "ПЧ": {
        "value": 2.0,
        "label": "ПЧ",
        "unit": "шт"
      },
      "Конверсія ПК": {
        "value": 59.43,
        "label": "Конверсія ПК",
        "unit": "%"
      },
      "Конверсія ПК Offline": {
        "value": 40.0,
        "label": "Конверсія ПК Offline",
        "unit": "%"
      },
      "УДС": {
        "value": 18049.9,
        "label": "УДС",
        "unit": "грн"
      },
      "Доля УДС": {
        "value": 10.9,
        "label": "Доля УДС",
        "unit": "%"
      }
    }
  },
  {
    "id": 4,
    "name": "Гайдей Максим Вікторович",
    "position": "продавец-консультант",
    "initials": "ГМ",
    "gradient": "linear-gradient(135deg, #f093fb 0%, #f5576c 100%)",
    "metrics": {
      "ТО": {
        "value": 29652.0,
        "label": "ТО",
        "unit": "грн"
      },
      "Шт.": {
        "value": 3.0,
        "label": "Шт.",
        "unit": "шт"
      },
      "Чеки": {
        "value": 2.0,
        "label": "Чеки",
        "unit": "шт"
      },
      "ASP": {
        "value": 9884.0,
        "label": "ASP",
        "unit": "грн"
      },
      "Ср. Чек": {
        "value": 14826.0,
        "label": "Ср. Чек",
        "unit": "грн"
      },
      "КПЧ": {
        "value": 1.5,
        "label": "КПЧ",
        "unit": "грн"
      },
      "ACC": {
        "value": 250.0,
        "label": "ACC",
        "unit": "грн"
      },
      "% Доля ACC": {
        "value": 0.84,
        "label": "% Доля ACC",
        "unit": "%"
      },
      "Послуги грн": {
        "value": 0.0,
        "label": "Послуги грн",
        "unit": "грн"
      },
      "Доля Послуг": {
        "value": 0.0,
        "label": "Доля Послуг",
        "unit": "%"
      },
      "ПЧ": {
        "value": 0.0,
        "label": "ПЧ",
        "unit": "шт"
      },
      "Конверсія ПК": {
        "value": 5.66,
        "label": "Конверсія ПК",
        "unit": "%"
      },
      "Конверсія ПК Offline": {
        "value": 2.86,
        "label": "Конверсія ПК Offline",
        "unit": "%"
      },
      "УДС": {
        "value": 0.0,
        "label": "УДС",
        "unit": "грн"
      },
      "Доля УДС": {
        "value": 0.0,
        "label": "Доля УДС",
        "unit": "%"
      }
    }
  },
  {
    "id": 5,
    "name": "Дідик Олександр Сергійович",
    "position": "продавец-консультант",
    "initials": "ДО",
    "gradient": "linear-gradient(135deg, #FF6B6B 0%, #EE5253 100%)",
    "metrics": {
      "ТО": {
        "value": 19014.0,
        "label": "ТО",
        "unit": "грн"
      },
      "Шт.": {
        "value": 10.0,
        "label": "Шт.",
        "unit": "шт"
      },
      "Чеки": {
        "value": 5.0,
        "label": "Чеки",
        "unit": "шт"
      },
      "ASP": {
        "value": 1901.0,
        "label": "ASP",
        "unit": "грн"
      },
      "Ср. Чек": {
        "value": 3803.0,
        "label": "Ср. Чек",
        "unit": "грн"
      },
      "КПЧ": {
        "value": 2.0,
        "label": "КПЧ",
        "unit": "грн"
      },
      "ACC": {
        "value": 6321.0,
        "label": "ACC",
        "unit": "грн"
      },
      "% Доля ACC": {
        "value": 33.24,
        "label": "% Доля ACC",
        "unit": "%"
      },
      "Послуги грн": {
        "value": 2399.0,
        "label": "Послуги грн",
        "unit": "грн"
      },
      "Доля Послуг": {
        "value": 12.62,
        "label": "Доля Послуг",
        "unit": "%"
      },
      "ПЧ": {
        "value": 1.0,
        "label": "ПЧ",
        "unit": "шт"
      },
      "Конверсія ПК": {
        "value": 14.15,
        "label": "Конверсія ПК",
        "unit": "%"
      },
      "Конверсія ПК Offline": {
        "value": 14.29,
        "label": "Конверсія ПК Offline",
        "unit": "%"
      },
      "УДС": {
        "value": 0.0,
        "label": "УДС",
        "unit": "грн"
      },
      "Доля УДС": {
        "value": 0.0,
        "label": "Доля УДС",
        "unit": "%"
      }
    }
  },
  {
    "id": 6,
    "name": "Сторожук Артем Олегович",
    "position": "продавец-консультант",
    "initials": "СА",
    "gradient": "linear-gradient(135deg, #4834d4 0%, #686de0 100%)",
    "metrics": {
      "ТО": {
        "value": 10068.0,
        "label": "ТО",
        "unit": "грн"
      },
      "Шт.": {
        "value": 1.0,
        "label": "Шт.",
        "unit": "шт"
      },
      "Чеки": {
        "value": 1.0,
        "label": "Чеки",
        "unit": "шт"
      },
      "ASP": {
        "value": 10068.0,
        "label": "ASP",
        "unit": "грн"
      },
      "Ср. Чек": {
        "value": 10068.0,
        "label": "Ср. Чек",
        "unit": "грн"
      },
      "КПЧ": {
        "value": 1.0,
        "label": "КПЧ",
        "unit": "грн"
      },
      "ACC": {
        "value": 0.0,
        "label": "ACC",
        "unit": "грн"
      },
      "% Доля ACC": {
        "value": 0.0,
        "label": "% Доля ACC",
        "unit": "%"
      },
      "Послуги грн": {
        "value": 0.0,
        "label": "Послуги грн",
        "unit": "грн"
      },
      "Доля Послуг": {
        "value": 0.0,
        "label": "Доля Послуг",
        "unit": "%"
      },
      "ПЧ": {
        "value": 0.0,
        "label": "ПЧ",
        "unit": "шт"
      },
      "Конверсія ПК": {
        "value": 2.83,
        "label": "Конверсія ПК",
        "unit": "%"
      },
      "Конверсія ПК Offline": {
        "value": 0.0,
        "label": "Конверсія ПК Offline",
        "unit": "%"
      },
      "УДС": {
        "value": 0.0,
        "label": "УДС",
        "unit": "грн"
      },
      "Доля УДС": {
        "value": 0.0,
        "label": "Доля УДС",
        "unit": "%"
      }
    }
  },
  {
    "id": 7,
    "name": "Михайлов Олександр Максимович",
    "position": "продавец-консультант",
    "initials": "МО",
    "gradient": "linear-gradient(135deg, #2ecc71 0%, #27ae60 100%)",
    "metrics": {
      "ТО": {
        "value": 4327.0,
        "label": "ТО",
        "unit": "грн"
      },
      "Шт.": {
        "value": 7.0,
        "label": "Шт.",
        "unit": "шт"
      },
      "Чеки": {
        "value": 4.0,
        "label": "Чеки",
        "unit": "шт"
      },
      "ASP": {
        "value": 618.0,
        "label": "ASP",
        "unit": "грн"
      },
      "Ср. Чек": {
        "value": 1082.0,
        "label": "Ср. Чек",
        "unit": "грн"
      },
      "КПЧ": {
        "value": 1.75,
        "label": "КПЧ",
        "unit": "грн"
      },
      "ACC": {
        "value": 3090.0,
        "label": "ACC",
        "unit": "грн"
      },
      "% Доля ACC": {
        "value": 71.4,
        "label": "% Доля ACC",
        "unit": "%"
      },
      "Послуги грн": {
        "value": 0.0,
        "label": "Послуги грн",
        "unit": "грн"
      },
      "Доля Послуг": {
        "value": 0.0,
        "label": "Доля Послуг",
        "unit": "%"
      },
      "ПЧ": {
        "value": 0.0,
        "label": "ПЧ",
        "unit": "шт"
      },
      "Конверсія ПК": {
        "value": 11.32,
        "label": "Конверсія ПК",
        "unit": "%"
      },
      "Конверсія ПК Offline": {
        "value": 5.71,
        "label": "Конверсія ПК Offline",
        "unit": "%"
      },
      "УДС": {
        "value": 0.0,
        "label": "УДС",
        "unit": "грн"
      },
      "Доля УДС": {
        "value": 0.0,
        "label": "Доля УДС",
        "unit": "%"
      }
    }
  },
  {
    "id": 8,
    "name": "Яковець Вікторія Володимирівна",
    "position": "кассир торгового зала",
    "initials": "ЯВ",
    "gradient": "linear-gradient(135deg, #f093fb 0%, #f5576c 100%)",
    "metrics": {
      "ТО": {
        "value": 439.0,
        "label": "ТО",
        "unit": "грн"
      },
      "Шт.": {
        "value": 1.0,
        "label": "Шт.",
        "unit": "шт"
      },
      "Чеки": {
        "value": 1.0,
        "label": "Чеки",
        "unit": "шт"
      },
      "ASP": {
        "value": 439.0,
        "label": "ASP",
        "unit": "грн"
      },
      "Ср. Чек": {
        "value": 439.0,
        "label": "Ср. Чек",
        "unit": "грн"
      },
      "КПЧ": {
        "value": 1.0,
        "label": "КПЧ",
        "unit": "грн"
      },
      "ACC": {
        "value": 439.0,
        "label": "ACC",
        "unit": "грн"
      },
      "% Доля ACC": {
        "value": 100.0,
        "label": "% Доля ACC",
        "unit": "%"
      },
      "Послуги грн": {
        "value": 0.0,
        "label": "Послуги грн",
        "unit": "грн"
      },
      "Доля Послуг": {
        "value": 0.0,
        "label": "Доля Послуг",
        "unit": "%"
      },
      "ПЧ": {
        "value": 0.0,
        "label": "ПЧ",
        "unit": "шт"
      },
      "Конверсія ПК": {
        "value": 2.83,
        "label": "Конверсія ПК",
        "unit": "%"
      },
      "Конверсія ПК Offline": {
        "value": 0.0,
        "label": "Конверсія ПК Offline",
        "unit": "%"
      },
      "УДС": {
        "value": 0.0,
        "label": "УДС",
        "unit": "грн"
      },
      "Доля УДС": {
        "value": 0.0,
        "label": "Доля УДС",
        "unit": "%"
      }
    }
  },
  {
    "id": 9,
    "name": "Савчук Денис Володимирович",
    "position": "продавец-консультант",
    "initials": "СД",
    "gradient": "linear-gradient(135deg, #FF6B6B 0%, #EE5253 100%)",
    "metrics": {
      "ТО": {
        "value": -470.0,
        "label": "ТО",
        "unit": "грн"
      },
      "Шт.": {
        "value": 0.0,
        "label": "Шт.",
        "unit": "шт"
      },
      "Чеки": {
        "value": 0.0,
        "label": "Чеки",
        "unit": "шт"
      },
      "ASP": {
        "value": 0.0,
        "label": "ASP",
        "unit": "грн"
      },
      "Ср. Чек": {
        "value": 0.0,
        "label": "Ср. Чек",
        "unit": "грн"
      },
      "КПЧ": {
        "value": 0.0,
        "label": "КПЧ",
        "unit": "грн"
      },
      "ACC": {
        "value": 0.0,
        "label": "ACC",
        "unit": "грн"
      },
      "% Доля ACC": {
        "value": 0.0,
        "label": "% Доля ACC",
        "unit": "%"
      },
      "Послуги грн": {
        "value": 0.0,
        "label": "Послуги грн",
        "unit": "грн"
      },
      "Доля Послуг": {
        "value": 0.0,
        "label": "Доля Послуг",
        "unit": "%"
      },
      "ПЧ": {
        "value": 0.0,
        "label": "ПЧ",
        "unit": "шт"
      },
      "Конверсія ПК": {
        "value": 0.0,
        "label": "Конверсія ПК",
        "unit": "%"
      },
      "Конверсія ПК Offline": {
        "value": 0.0,
        "label": "Конверсія ПК Offline",
        "unit": "%"
      },
      "УДС": {
        "value": 0.0,
        "label": "УДС",
        "unit": "грн"
      },
      "Доля УДС": {
        "value": 0.0,
        "label": "Доля УДС",
        "unit": "%"
      }
    }
  }
]